hello_labdata_gbm/__init__.py
hello_labdata_gbm/_modidx.py
hello_labdata_gbm/greetings.py
hello_labdata_gbm/jokes.py
hello_labdata_gbm-0.0.2.dist-info/LICENSE
hello_labdata_gbm-0.0.2.dist-info/METADATA
hello_labdata_gbm-0.0.2.dist-info/WHEEL
hello_labdata_gbm-0.0.2.dist-info/entry_points.txt
hello_labdata_gbm-0.0.2.dist-info/top_level.txt
hello_labdata_gbm-0.0.2.dist-info/RECORD
