Metadata-Version: 2.1
Name: hello-labdata-gbm
Version: 0.0.2
Summary: Labdata Hello Python Package
Home-page: https://github.com/gabmarques88/hello-labdata-gbm/
Author: gabmarques88
Author-email: gab.bezerra88@gmail.com
License: Apache Software License 2.0
Keywords: nbdev
Classifier: Development Status :: 3 - Alpha
Classifier: Intended Audience :: Developers
Classifier: Natural Language :: English
Classifier: Programming Language :: Python :: 3.9
Classifier: Programming Language :: Python :: 3.10
Classifier: License :: OSI Approved :: Apache Software License
Requires-Python: >=3.9
License-File: LICENSE
Provides-Extra: dev
